LICENSE
mqtt_to_pagerduty/__init__.py
mqtt_to_pagerduty/cli.py
mqtt_to_pagerduty/emitter.py
mqtt_to_pagerduty/processor.py
mqtt_to_pagerduty/settings.py
mqtt_to_pagerduty-0.2.1.dist-info/entry_points.txt
mqtt_to_pagerduty-0.2.1.dist-info/LICENSE
mqtt_to_pagerduty-0.2.1.dist-info/WHEEL
mqtt_to_pagerduty-0.2.1.dist-info/METADATA
mqtt_to_pagerduty-0.2.1.dist-info/RECORD
