Metadata-Version: 2.1
Name: mqtt-to-pagerduty
Version: 0.2.1
Summary: Read messages in a MQTT topic and create PagerDuty alerts
Home-page: https://github.com/unixorn/mqtt-to-pagerduty
License: Apache
Keywords: PagerDuty,mqtt
Author: Joe Block
Author-email: jpb@unixorn.net
Requires-Python: >=3.9,<4.0
Classifier: License :: Other/Proprietary License
Classifier: Programming Language :: Python :: 3
Classifier: Programming Language :: Python :: 3.10
Classifier: Programming Language :: Python :: 3.9
Requires-Dist: paho-mqtt (>=1.6.1,<2.0.0)
Requires-Dist: pdcrier (>=0.2.0,<0.3.0)
Requires-Dist: pyaml (>=21.10.1,<22.0.0)
Requires-Dist: thelogrus (>=0.6.3,<0.7.0)
Project-URL: Bug Tracker, https://github.com/unixorn/mqtt-to-pagerduty/issues
Project-URL: Documentation, https://github.com/unixorn/mqtt-to-pagerduty
Project-URL: Repository, https://github.com/unixorn/mqtt-to-pagerduty
